gold33423310/__init__.py
gold33423310/gold.py
gold33423310-0.0.1.dist-info/LICENSE
gold33423310-0.0.1.dist-info/METADATA
gold33423310-0.0.1.dist-info/WHEEL
gold33423310-0.0.1.dist-info/top_level.txt
gold33423310-0.0.1.dist-info/RECORD
