Metadata-Version: 2.1
Name: gold33423310
Version: 0.0.1
Summary: gold
Home-page: https://github.com/syahrulcaem/gold33423310
Author: hanifaslamm
Author-email: <aslamhanif141@gmail.com>
License: MIT
Keywords: gold,33423310
Classifier: Development Status :: 1 - Planning
License-File: LICENSE
